pyrheadb/AtomMapper.py
pyrheadb/RInChI.py
pyrheadb/Reaction.py
pyrheadb/ReactionNetwork.py
pyrheadb/ReactionPrediction.py
pyrheadb/ReactionSmartsConverter.py
pyrheadb/RheaCobraModel.py
pyrheadb/RheaDB.py
pyrheadb/RheaSPARQL.py
pyrheadb/Visualization.py
pyrheadb/__init__.py
pyrheadb/bin/rinchi_lib/linux/armv6l/librinchi.so.1.0.0
pyrheadb/bin/rinchi_lib/linux/x86/librinchi.so.1.0.0
pyrheadb/bin/rinchi_lib/linux/x86_64/librinchi.so.1.0.0
pyrheadb/bin/rinchi_lib/mac/arm64/librinchi.dylib.1.0.0
pyrheadb/bin/rinchi_lib/windows/x86/librinchi.dll
pyrheadb/bin/rinchi_lib/windows/x86_64/librinchi.dll
pyrheadb/biochemical_assumptions/default_metabolic_precursor_molecules.tsv
pyrheadb/biochemical_assumptions/default_metabolic_precursor_molecules_with_manual_check.tsv
pyrheadb/biochemical_assumptions/note on inorganics in biochemistry.txt
pyrheadb/biochemical_assumptions/rhea_chebi_hub.tsv
pyrheadb/modeling_assumptions/objective_functions
pyrheadb-0.1.8.dist-info/METADATA
pyrheadb-0.1.8.dist-info/WHEEL
pyrheadb-0.1.8.dist-info/top_level.txt
pyrheadb-0.1.8.dist-info/RECORD
