Metadata-Version: 2.4
Name: pyrheadb
Version: 0.1.8
Summary: Package to facilitate cheminformatics access to RheaDB and its analysis with Python
Author-email: Anastasia Sveshnikova <anastasia.sveshnikova@sib.swiss>
Project-URL: Homepage, https://github.com/sib-swiss/pyrheadb
Project-URL: Issues, https://github.com/sib-swiss/pyrheadb/issues
Classifier: Programming Language :: Python :: 3
Classifier: Programming Language :: Python :: 3.8
Classifier: Programming Language :: Python :: 3.9
Classifier: Programming Language :: Python :: 3.10
Classifier: Programming Language :: Python :: 3.11
Classifier: Operating System :: POSIX :: Linux
Classifier: Operating System :: MacOS :: MacOS X
Classifier: Operating System :: Microsoft :: Windows
Requires-Python: >=3.8
Requires-Dist: setuptools
Requires-Dist: pandas
Requires-Dist: rdkit
Requires-Dist: requests_ftp
Requires-Dist: networkx
Requires-Dist: tqdm
Requires-Dist: matplotlib
Requires-Dist: pathlib
Requires-Dist: rxnmapper
Requires-Dist: pillow
Requires-Dist: cobra
Requires-Dist: sparqlwrapper
Requires-Dist: jupyterlab
Provides-Extra: test
Requires-Dist: pytest>=7.1.3; extra == "test"
Requires-Dist: pytest-cov>=3.0.0; extra == "test"
Requires-Dist: mypy>=1.4.1; extra == "test"
